<?xml version="1.0" encoding="UTF-8" standalone="yes"?>
<gameWorld>
    <rooms>
        <rooms>
            <item>
                <contents>
                    <entry>
                        <key>NORTH</key>
                        <value/>
                    </entry>
                </contents>
                <walls>
                    <entry>
                        <key>NORTH</key>
                        <value>
                            <direction>NORTH</direction>
                            <visible>true</visible>
                        </value>
                    </entry>
                    <entry>
                        <key>WEST</key>
                        <value>
                            <direction>WEST</direction>
                            <visible>true</visible>
                        </value>
                    </entry>
                    <entry>
                        <key>SOUTH</key>
                        <value>
                            <direction>SOUTH</direction>
                            <door>
<color>
    <b>255</b>
    <g>0</g>
    <r>0</r>
</color>
<isLocked>false</isLocked>
                            </door>
                            <visible>true</visible>
                        </value>
                    </entry>
                    <entry>
                        <key>EAST</key>
                        <value>
                            <direction>EAST</direction>
                            <door>
<color>
    <b>255</b>
    <g>0</g>
    <r>0</r>
</color>
<isLocked>false</isLocked>
                            </door>
                            <visible>true</visible>
                        </value>
                    </entry>
                </walls>
                <x>0</x>
                <y>0</y>
            </item>
        </rooms>
    </rooms>
    <player>
        <inventory xmlns:xsi="http://www.w3.org/2001/XMLSchema-instance" xsi:type="keyComponent">
            <color>
                <b>255</b>
                <g>0</g>
                <r>0</r>
            </color>
            <depth>1</depth>
            <description>A Nice Pen</description>
            <direction>NORTH</direction>
            <height>1</height>
            <name>Pen</name>
            <width>1</width>
            <x>1</x>
            <y>1</y>
            <z>1</z>
        </inventory>
        <inventory xmlns:xsi="http://www.w3.org/2001/XMLSchema-instance" xsi:type="keyComponent">
            <color>
                <b>255</b>
                <g>0</g>
                <r>0</r>
            </color>
            <depth>1</depth>
            <description>Greenery</description>
            <direction>NORTH</direction>
            <height>50</height>
            <name>Pot plant</name>
            <width>50</width>
            <x>5</x>
            <y>5</y>
            <z>1</z>
        </inventory>
        <inventory xmlns:xsi="http://www.w3.org/2001/XMLSchema-instance" xsi:type="keyComponent">
            <color>
                <b>255</b>
                <g>0</g>
                <r>0</r>
            </color>
            <depth>1</depth>
            <description>its A Painting</description>
            <direction>NORTH</direction>
            <height>50</height>
            <name>Painting</name>
            <width>50</width>
            <x>7</x>
            <y>10</y>
            <z>1</z>
        </inventory>
        <inventory xmlns:xsi="http://www.w3.org/2001/XMLSchema-instance" xsi:type="keyComponent">
            <color>
                <b>255</b>
                <g>0</g>
                <r>0</r>
            </color>
            <depth>1</depth>
            <description>its A Chair</description>
            <direction>NORTH</direction>
            <height>50</height>
            <name>Chair</name>
            <width>50</width>
            <x>2</x>
            <y>15</y>
            <z>1</z>
        </inventory>
        <inventory xmlns:xsi="http://www.w3.org/2001/XMLSchema-instance" xsi:type="keyComponent">
            <color>
                <b>255</b>
                <g>0</g>
                <r>0</r>
            </color>
            <depth>1</depth>
            <description>its A Table </description>
            <direction>NORTH</direction>
            <height>50</height>
            <name>Table</name>
            <width>50</width>
            <x>6</x>
            <y>9</y>
            <z>1</z>
        </inventory>
        <inventory xmlns:xsi="http://www.w3.org/2001/XMLSchema-instance" xsi:type="keyComponent">
            <color>
                <b>255</b>
                <g>0</g>
                <r>0</r>
            </color>
            <depth>1</depth>
            <description>its A af</description>
            <direction>NORTH</direction>
            <height>50</height>
            <name>ds</name>
            <width>50</width>
            <x>2</x>
            <y>15</y>
            <z>1</z>
        </inventory>
        <inventory xmlns:xsi="http://www.w3.org/2001/XMLSchema-instance" xsi:type="keyComponent">
            <color>
                <b>255</b>
                <g>0</g>
                <r>0</r>
            </color>
            <depth>1</depth>
            <description>its A af</description>
            <direction>NORTH</direction>
            <height>50</height>
            <name>ds</name>
            <width>50</width>
            <x>2</x>
            <y>15</y>
            <z>1</z>
        </inventory>
        <inventory xmlns:xsi="http://www.w3.org/2001/XMLSchema-instance" xsi:type="keyComponent">
            <color>
                <b>255</b>
                <g>0</g>
                <r>0</r>
            </color>
            <depth>1</depth>
            <description>its A af</description>
            <direction>NORTH</direction>
            <height>50</height>
            <name>ds</name>
            <width>50</width>
            <x>2</x>
            <y>15</y>
            <z>1</z>
        </inventory>
        <inventory xmlns:xsi="http://www.w3.org/2001/XMLSchema-instance" xsi:type="keyComponent">
            <color>
                <b>255</b>
                <g>0</g>
                <r>0</r>
            </color>
            <depth>1</depth>
            <description>its A af</description>
            <direction>NORTH</direction>
            <height>50</height>
            <name>ds</name>
            <width>50</width>
            <x>2</x>
            <y>15</y>
            <z>1</z>
        </inventory>
        <inventory xmlns:xsi="http://www.w3.org/2001/XMLSchema-instance" xsi:type="keyComponent">
            <color>
                <b>255</b>
                <g>0</g>
                <r>0</r>
            </color>
            <depth>1</depth>
            <description>its A af</description>
            <direction>NORTH</direction>
            <height>50</height>
            <name>ds</name>
            <width>50</width>
            <x>2</x>
            <y>15</y>
            <z>1</z>
        </inventory>
        <inventory xmlns:xsi="http://www.w3.org/2001/XMLSchema-instance" xsi:type="keyComponent">
            <color>
                <b>255</b>
                <g>0</g>
                <r>0</r>
            </color>
            <depth>1</depth>
            <description>its A af</description>
            <direction>NORTH</direction>
            <height>50</height>
            <name>ds</name>
            <width>50</width>
            <x>2</x>
            <y>15</y>
            <z>1</z>
        </inventory>
        <perspective>NORTH</perspective>
        <x>0</x>
        <y>0</y>
    </player>
</gameWorld>
